delpinos/api/flask/controllers/flask_controller.py
delpinos/api/flask/encoders/flask_encoder.py
delpinos/api/flask/factories/flask_factory.py
delpinos/api/flask/requests/flask_request.py
delpinos/api/flask/responses/flask_response.py
delpinos_api_flask-0.0.4.dist-info/METADATA
delpinos_api_flask-0.0.4.dist-info/WHEEL
delpinos_api_flask-0.0.4.dist-info/top_level.txt
delpinos_api_flask-0.0.4.dist-info/RECORD
